odoo/addons/ecommerce_connector/README.rst
odoo/addons/ecommerce_connector/__init__.py
odoo/addons/ecommerce_connector/__manifest__.py
odoo/addons/ecommerce_connector/data/ecommerce_connector_call_seq.xml
odoo/addons/ecommerce_connector/models/__init__.py
odoo/addons/ecommerce_connector/models/account_move.py
odoo/addons/ecommerce_connector/models/account_move_line.py
odoo/addons/ecommerce_connector/models/account_payment.py
odoo/addons/ecommerce_connector/models/ecommerce_connection.py
odoo/addons/ecommerce_connector/models/ecommerce_connector.py
odoo/addons/ecommerce_connector/models/ecommerce_connector_call.py
odoo/addons/ecommerce_connector/models/ecommerce_partner.py
odoo/addons/ecommerce_connector/models/ecommerce_product_product.py
odoo/addons/ecommerce_connector/models/ecommerce_product_template.py
odoo/addons/ecommerce_connector/models/product_pricelist.py
odoo/addons/ecommerce_connector/models/product_product.py
odoo/addons/ecommerce_connector/models/product_template.py
odoo/addons/ecommerce_connector/models/product_template_attribute_value.py
odoo/addons/ecommerce_connector/models/res_company.py
odoo/addons/ecommerce_connector/models/res_partner.py
odoo/addons/ecommerce_connector/models/sale_order.py
odoo/addons/ecommerce_connector/models/sale_order_line.py
odoo/addons/ecommerce_connector/readme/CONFIGURE.md
odoo/addons/ecommerce_connector/readme/CONTRIBUTORS.md
odoo/addons/ecommerce_connector/readme/DESCRIPTION.md
odoo/addons/ecommerce_connector/readme/INSTALL.md
odoo/addons/ecommerce_connector/readme/USAGE.md
odoo/addons/ecommerce_connector/security/ir.model.access.csv
odoo/addons/ecommerce_connector/static/description/ecommerce_connector_icon.png
odoo/addons/ecommerce_connector/static/description/icon.png
odoo/addons/ecommerce_connector/static/description/index.html
odoo/addons/ecommerce_connector/views/ecommerce_connection_views.xml
odoo/addons/ecommerce_connector/views/ecommerce_connector_call_views.xml
odoo_addon_ecommerce_connector-15.0.3.0.1.dist-info/METADATA
odoo_addon_ecommerce_connector-15.0.3.0.1.dist-info/WHEEL
odoo_addon_ecommerce_connector-15.0.3.0.1.dist-info/top_level.txt
odoo_addon_ecommerce_connector-15.0.3.0.1.dist-info/RECORD
