Metadata-Version: 2.1
Name: odoo-addon-ecommerce_connector
Version: 15.0.3.0.1
Requires-Python: >=3.8
Requires-Dist: odoo-addon-account_fiscal_position_partner_type>=15.0dev,<15.1dev
Requires-Dist: odoo-addon-account_payment_mode>=15.0dev,<15.1dev
Requires-Dist: odoo-addon-account_payment_sale>=15.0dev,<15.1dev
Requires-Dist: odoo>=15.0a,<15.1dev
Summary: General E-Commerce Integration
Home-page: https://github.com/sygel-technology/sy-general-connector
License: AGPL-3
Author: Sygel
Classifier: Programming Language :: Python
Classifier: Framework :: Odoo
Classifier: Framework :: Odoo :: 15.0
Classifier: License :: OSI Approved :: GNU Affero General Public License v3
